LICENSE
MANIFEST.in
README.md
setup.cfg
setup.py
di/__init__.py
di/main.py
di_py.egg-info/PKG-INFO
di_py.egg-info/SOURCES.txt
di_py.egg-info/dependency_links.txt
di_py.egg-info/not-zip-safe
di_py.egg-info/top_level.txt