Metadata-Version: 1.0
Name: di-py
Version: 1.2.0
Summary: Dependency injection library
Home-page: https://www.github.com/telefonicaid/di-py
Author: Telefonica Digital
Author-email: connect-dev@tid.es
License: UNKNOWN
Platform: UNKNOWN
